message_media_messages/__init__.py
message_media_messages/api_helper.py
message_media_messages/configuration.py
message_media_messages/decorators.py
message_media_messages/message_media_messages_client.py
message_media_messages/controllers/__init__.py
message_media_messages/controllers/base_controller.py
message_media_messages/controllers/delivery_reports_controller.py
message_media_messages/controllers/messages_controller.py
message_media_messages/controllers/replies_controller.py
message_media_messages/exceptions/__init__.py
message_media_messages/exceptions/api_exception.py
message_media_messages/exceptions/send_messages_400_response_exception.py
message_media_messages/http/__init__.py
message_media_messages/http/http_call_back.py
message_media_messages/http/http_client.py
message_media_messages/http/http_context.py
message_media_messages/http/http_method_enum.py
message_media_messages/http/http_request.py
message_media_messages/http/http_response.py
message_media_messages/http/requests_client.py
message_media_messages/http/auth/__init__.py
message_media_messages/http/auth/auth_manager.py
message_media_messages/models/__init__.py
message_media_messages/models/cancel_scheduled_message_request.py
message_media_messages/models/check_delivery_reports_response.py
message_media_messages/models/check_replies_response.py
message_media_messages/models/confirm_delivery_reports_as_received_request.py
message_media_messages/models/confirm_delivery_reports_as_received_request_1.py
message_media_messages/models/confirm_replies_as_received_request.py
message_media_messages/models/confirm_replies_as_received_request_1.py
message_media_messages/models/delivery_report.py
message_media_messages/models/format_1_enum.py
message_media_messages/models/format_enum.py
message_media_messages/models/get_message_status_response.py
message_media_messages/models/message.py
message_media_messages/models/reply.py
message_media_messages/models/send_messages_request.py
messagemedia_messages_sdk-2.1.3.dist-info/LICENSE
messagemedia_messages_sdk-2.1.3.dist-info/METADATA
messagemedia_messages_sdk-2.1.3.dist-info/WHEEL
messagemedia_messages_sdk-2.1.3.dist-info/top_level.txt
messagemedia_messages_sdk-2.1.3.dist-info/RECORD
