Metadata-Version: 2.1
Name: messagemedia-messages-sdk
Version: 2.1.3
Summary: The MessageMedia Messages API provides a number of endpoints for building powerful two-way messaging applications.
Home-page: https://developers.messagemedia.com
Author: MessageMedia Developers
Author-email: developers@messagemedia.com
License-File: LICENSE
Requires-Dist: requests<3.0,>=2.28.2
Requires-Dist: jsonpickle<4.0,>=3.0.1
Requires-Dist: cachecontrol<1.0,>=0.12.11
Requires-Dist: python-dateutil<3.0,>=2.8.2
Requires-Dist: responses<1.0,>=0.22.0
Requires-Dist: urllib3<2.0,>=1.26.14
Requires-Dist: setuptools<68,>=67.2.0
